advent_of_code_hhoppe/__init__.py
advent_of_code_hhoppe/py.typed
advent_of_code_hhoppe-1.1.2.dist-info/licenses/LICENSE
advent_of_code_hhoppe-1.1.2.dist-info/WHEEL
advent_of_code_hhoppe-1.1.2.dist-info/METADATA
advent_of_code_hhoppe-1.1.2.dist-info/RECORD
