Metadata-Version: 2.4
Name: advent-of-code-hhoppe
Version: 1.1.2
Summary: Library for Advent of Code -- Hugues Hoppe.
Keywords: 
Author-email: Hugues Hoppe <hhoppe@gmail.com>
Requires-Python: >=3.10
Classifier: Programming Language :: Python :: 3
Classifier: License :: OSI Approved :: MIT License
Classifier: Operating System :: OS Independent
License-File: LICENSE
Requires-Dist: advent-of-code-data
Requires-Dist: IPython
Project-URL: homepage, https://github.com/hhoppe/advent-of-code-hhoppe
Project-URL: repository, https://github.com/hhoppe/advent-of-code-hhoppe
Provides-Extra: dev
